swb/__init__.py
swb/crop_evapotranspiration.py
swb/effective_precipitation.py
swb/swb.py
swb-5.0.1.dist-info/LICENSE
swb-5.0.1.dist-info/METADATA
swb-5.0.1.dist-info/WHEEL
swb-5.0.1.dist-info/top_level.txt
swb-5.0.1.dist-info/RECORD
