Metadata-Version: 2.1
Name: swb
Version: 5.0.1
Summary: Calculation of soil water balance
Home-page: https://github.com/openmeteo/swb
Author: Antonis Christofides
Author-email: antonis@antonischristofides.com
License: GNU General Public License v3
Classifier: Development Status :: 2 - Pre-Alpha
Classifier: Intended Audience :: Developers
Classifier: License :: OSI Approved :: GNU General Public License v3 (GPLv3)
Classifier: Natural Language :: English
Classifier: Programming Language :: Python :: 3.5
Classifier: Programming Language :: Python :: 3.6
License-File: LICENSE
Requires-Dist: pandas >=0.20
